dx_eurocode/__init__.py
dx_eurocode/EC0/__init__.py
dx_eurocode/EC0/safety_factors.py
dx_eurocode/EC2/__init__.py
dx_eurocode/EC2/formulas.py
dx_eurocode/EC2/materials.py
dx_eurocode/EC2/safety_factors.py
dx_eurocode-1.0.0.dist-info/LICENSE
dx_eurocode-1.0.0.dist-info/METADATA
dx_eurocode-1.0.0.dist-info/WHEEL
dx_eurocode-1.0.0.dist-info/top_level.txt
dx_eurocode-1.0.0.dist-info/RECORD
