Metadata-Version: 2.1
Name: dx-eurocode
Version: 1.0.0
Summary: Base package for structural design with Eurocodes
Home-page: https://gitlab.com/d-e/dx-eurocode
Author: Konstantinos Demartinos
Author-email: kostas@d-e.gr
Maintainer: demetriou engineering ltd.
Maintainer-email: kostas@d-e.gr
License: AGPLv3+
Keywords: structural-design,eurocode
Platform: UNKNOWN
Classifier: Programming Language :: Python :: 3
Classifier: License :: OSI Approved :: GNU Affero General Public License v3 or later (AGPLv3+)
Classifier: Operating System :: OS Independent
Classifier: Topic :: Scientific/Engineering
Requires-Dist: dx-base (<2.0.0,>=1.0.0)
